LICENSE
README.rst
setup.cfg
setup.py
word_counter/__init__.py
word_counter/__main__.py
word_counter/commands.py
word_counter.egg-info/PKG-INFO
word_counter.egg-info/SOURCES.txt
word_counter.egg-info/dependency_links.txt
word_counter.egg-info/entry_points.txt
word_counter.egg-info/requires.txt
word_counter.egg-info/top_level.txt