Metadata-Version: 1.2
Name: word-counter
Version: 0.0.2
Summary: Count the number of words on the specified URL(s).
Home-page: https://github.com/sig9org/word-counter
Author: sig9
Author-email: sig9@sig9.org
Maintainer: sig9
Maintainer-email: sig9@sig9.org
License: MIT License
Keywords: Count,Morphological analysis,Split,Word
Platform: POSIX
Platform: Windows
Platform: Unix
Platform: MacOS
Classifier: Intended Audience :: Developers
Classifier: License :: OSI Approved :: MIT License
Classifier: Natural Language :: Japanese
Classifier: Operating System :: MacOS
Classifier: Operating System :: Microsoft
Classifier: Operating System :: POSIX
Classifier: Operating System :: OS Independent
Classifier: Programming Language :: Python :: 3 :: Only
Classifier: Programming Language :: Python :: 3.4
Classifier: Programming Language :: Python :: 3.5
Classifier: Programming Language :: Python :: 3.6
Classifier: Programming Language :: Python :: 3.7
Classifier: Programming Language :: Python :: 3.8
